README.txt
setup.py
gpta/__init__.py
gpta/cat.py
gpta/dump.py
gpta/mm_analysis.py
gpta/plot.py
gpta.egg-info/PKG-INFO
gpta.egg-info/SOURCES.txt
gpta.egg-info/dependency_links.txt
gpta.egg-info/entry_points.txt
gpta.egg-info/requires.txt
gpta.egg-info/top_level.txt