Metadata-Version: 1.0
Name: gpta
Version: 0.0.8
Summary: gpta
Home-page: https://github.com/guoxiaoyong/gpta
Author: Guo Xiaoyong
Author-email: guo.xiaoyong@gmail.com
License: UNKNOWN
Platform: UNKNOWN
